{
  "project_info": {
    "project_number": "433931523568",
    "project_id": "vansh9867-2a778",
    "storage_bucket": "vansh9867-2a778.appspot.com"
  },
  "client": [
    {
      "client_info": {
        "mobilesdk_app_id": "1:433931523568:android:96da3273bb14681eb9b935",
        "android_client_info": {
          "package_name": "com.demo777"
        }
      },
      "oauth_client": [
        {
          "client_id": "433931523568-5kmj7js63gnf35d9qoh3gttt3l6a4n4m.apps.googleusercontent.com",
          "client_type": 3
        }
      ],
      "api_key": [
        {
          "current_key": "AIzaSyAS8O0HvFOMIOw_l9xTxZnEL40y6aHKlX0"
        }
      ],
      "services": {
        "appinvite_service": {
          "other_platform_oauth_client": [
            {
              "client_id": "433931523568-5kmj7js63gnf35d9qoh3gttt3l6a4n4m.apps.googleusercontent.com",
              "client_type": 3
            }
          ]
        }
      }
    },
    {
      "client_info": {
        "mobilesdk_app_id": "1:433931523568:android:57c844db97424dc3b9b935",
        "android_client_info": {
          "package_name": "com.ecommerce777"
        }
      },
      "oauth_client": [
        {
          "client_id": "433931523568-bru85da99qcqc3oe633bdiikffh3oras.apps.googleusercontent.com",
          "client_type": 1,
          "android_info": {
            "package_name": "com.ecommerce777",
            "certificate_hash": "5e8f16062ea3cd2c4a0d547876baa6f38cabf625"
          }
        },
        {
          "client_id": "433931523568-5kmj7js63gnf35d9qoh3gttt3l6a4n4m.apps.googleusercontent.com",
          "client_type": 3
        }
      ],
      "api_key": [
        {
          "current_key": "AIzaSyAS8O0HvFOMIOw_l9xTxZnEL40y6aHKlX0"
        }
      ],
      "services": {
        "appinvite_service": {
          "other_platform_oauth_client": [
            {
              "client_id": "433931523568-5kmj7js63gnf35d9qoh3gttt3l6a4n4m.apps.googleusercontent.com",
              "client_type": 3
            }
          ]
        }
      }
    },
    {
      "client_info": {
        "mobilesdk_app_id": "1:433931523568:android:7b404de5b6969f55b9b935",
        "android_client_info": {
          "package_name": "com.ecommercevanshadmin"
        }
      },
      "oauth_client": [
        {
          "client_id": "433931523568-5kmj7js63gnf35d9qoh3gttt3l6a4n4m.apps.googleusercontent.com",
          "client_type": 3
        }
      ],
      "api_key": [
        {
          "current_key": "AIzaSyAS8O0HvFOMIOw_l9xTxZnEL40y6aHKlX0"
        }
      ],
      "services": {
        "appinvite_service": {
          "other_platform_oauth_client": [
            {
              "client_id": "433931523568-5kmj7js63gnf35d9qoh3gttt3l6a4n4m.apps.googleusercontent.com",
              "client_type": 3
            }
          ]
        }
      }
    }
  ],
  "configuration_version": "1"
}